LICENSE
MANIFEST.in
README.md
setup.py
upload_machine/__init__.py
upload_machine/basicinfo.yaml
upload_machine/main.py
upload_machine.egg-info/PKG-INFO
upload_machine.egg-info/SOURCES.txt
upload_machine.egg-info/dependency_links.txt
upload_machine.egg-info/entry_points.txt
upload_machine.egg-info/requires.txt
upload_machine.egg-info/top_level.txt
upload_machine/utils/__init__.py
upload_machine/utils/edittorrent/__init__.py
upload_machine/utils/edittorrent/edittorrent.py
upload_machine/utils/img_upload/__init__.py
upload_machine/utils/img_upload/chevereto.py
upload_machine/utils/img_upload/fapping_emp.py
upload_machine/utils/img_upload/imgbox.py
upload_machine/utils/img_upload/imgupload.py
upload_machine/utils/img_upload/ptpimg.py
upload_machine/utils/img_upload/redleaves.py
upload_machine/utils/img_upload/rousi.py
upload_machine/utils/img_upload/sharkimg.py
upload_machine/utils/img_upload/smms.py
upload_machine/utils/mediafile/__init__.py
upload_machine/utils/mediafile/douban_book.py
upload_machine/utils/mediafile/douban_movie.py
upload_machine/utils/mediafile/doubaninfo.py
upload_machine/utils/mediafile/maketorrent.py
upload_machine/utils/mediafile/mediafile.py
upload_machine/utils/para_ctrl/__init__.py
upload_machine/utils/para_ctrl/para_ctrl.py
upload_machine/utils/para_ctrl/readargs.py
upload_machine/utils/para_ctrl/readyaml.py
upload_machine/utils/pathinfo/__init__.py
upload_machine/utils/pathinfo/pathinfo.py
upload_machine/utils/rss_ctrl/__init__.py
upload_machine/utils/seed_machine/__init__.py
upload_machine/utils/seed_machine/seed_machine.py
upload_machine/utils/signer/__init__.py
upload_machine/utils/site/__init__.py
upload_machine/utils/site/site.py
upload_machine/utils/uploader/__init__.py
upload_machine/utils/uploader/audience_upload.py
upload_machine/utils/uploader/auto_upload.py
upload_machine/utils/uploader/carpt_upload.py
upload_machine/utils/uploader/dajiao_upload.py
upload_machine/utils/uploader/hares_upload.py
upload_machine/utils/uploader/hdfans_upload.py
upload_machine/utils/uploader/hdpt_upload.py
upload_machine/utils/uploader/hdsky_upload.py
upload_machine/utils/uploader/hdvideo_upload.py
upload_machine/utils/uploader/hhclub_upload.py
