Metadata-Version: 2.1
Name: upload-machine
Version: 0.0.89
Summary: Upload local resources to PT trackers automatically.
Home-page: https://github.com/dongshuyan/Upload_Machine
Author: sauterne
Author-email: ssauterne@qq.com
License: MIT Licence
Keywords: pip,autoupload,auto,upload,PT,private tracker
Platform: any
Requires-Python: >=3
License-File: LICENSE
